hype/__init__.py
hype/admin.py
hype/middleware.py
hype/migrations/0001_initial.py
hype/migrations/__init__.py
hype/models.py
hype/settings.py
hype/urls.py
hype/views.py
django_hype-1.0.0.dist-info/LICENSE
django_hype-1.0.0.dist-info/WHEEL
django_hype-1.0.0.dist-info/METADATA
django_hype-1.0.0.dist-info/RECORD
