Metadata-Version: 2.1
Name: django-hype
Version: 1.0.0
Summary: Referral links for Django
License: MIT
Keywords: django,referral,links
Author: Justin Mayer
Author-email: entroP@gmail.com
Requires-Python: >=3.7,<4.0
Classifier: Development Status :: 5 - Production/Stable
Classifier: Framework :: Django
Classifier: License :: OSI Approved :: MIT License
Classifier: Operating System :: OS Independent
Classifier: Programming Language :: Python :: 3
Classifier: Programming Language :: Python :: 3.7
Classifier: Programming Language :: Python :: 3.8
Classifier: Programming Language :: Python :: 3.9
Classifier: Programming Language :: Python :: 3.10
Classifier: Programming Language :: Python :: 3.11
Requires-Dist: Django (>=3.2)
Project-URL: Funding, https://github.com/sponsors/justinmayer
Project-URL: Issue Tracker, https://github.com/justinmayer/django-hype/issues
